ld_flag_lookup/main.py
ld_flag_lookup-1.0.0.dist-info/METADATA
ld_flag_lookup-1.0.0.dist-info/WHEEL
ld_flag_lookup-1.0.0.dist-info/entry_points.txt
ld_flag_lookup-1.0.0.dist-info/RECORD
