Metadata-Version: 2.1
Name: ld-flag-lookup
Version: 1.0.0
Summary: Lookup LaunchDarkly feature flags by key and return their values.
Home-page: https://github.com/chkpwd/ld-flag-lookup
License: MIT
Author: Bryan Jones
Author-email: unix.chkpwd@gmail.com
Requires-Python: >=3.11,<4.0
Classifier: License :: OSI Approved :: MIT License
Classifier: Programming Language :: Python :: 3
Classifier: Programming Language :: Python :: 3.11
Classifier: Programming Language :: Python :: 3.12
Requires-Dist: click (>=8.1.7)
Requires-Dist: launchdarkly-server-sdk (>=9.0.0)
Project-URL: Repository, https://github.com/chkpwd/ld-flag-lookup
